tr_toolbox/__init__.py
tr_toolbox-0.0.1.dist-info/licenses/LICENSE
tr_toolbox-0.0.1.dist-info/METADATA
tr_toolbox-0.0.1.dist-info/WHEEL
tr_toolbox-0.0.1.dist-info/top_level.txt
tr_toolbox-0.0.1.dist-info/RECORD
