Metadata-Version: 2.4
Name: tr_toolbox
Version: 0.0.1
Summary: Türkçe metin işlemleri ve URL slug için yardımcı araçlar.
Author-email: Sema <viranora@gmail.com>
Project-URL: Homepage, https://github.com/viranora/tr_toolbox
Classifier: Programming Language :: Python :: 3
Classifier: License :: OSI Approved :: MIT License
Classifier: Operating System :: OS Independent
Classifier: Topic :: Text Processing
Classifier: Topic :: Utilities
Requires-Python: >=3.7
License-File: LICENSE
Dynamic: license-file
